LICENSE
MANIFEST.in
README.md
setup.py
django_search_filter_sort.egg-info/PKG-INFO
django_search_filter_sort.egg-info/SOURCES.txt
django_search_filter_sort.egg-info/dependency_links.txt
django_search_filter_sort.egg-info/top_level.txt
search_filter_sort/__init__.py
search_filter_sort/admin.py
search_filter_sort/apps.py
search_filter_sort/models.py
search_filter_sort/tests.py
search_filter_sort/locale/en_US/LC_MESSAGES/django.mo
search_filter_sort/locale/en_US/LC_MESSAGES/django.po
search_filter_sort/locale/es_MX/LC_MESSAGES/django.mo
search_filter_sort/locale/es_MX/LC_MESSAGES/django.po
search_filter_sort/locale/zh_Hans/LC_MESSAGES/django.mo
search_filter_sort/locale/zh_Hans/LC_MESSAGES/django.po
search_filter_sort/locale/zh_Hant/LC_MESSAGES/django.mo
search_filter_sort/locale/zh_Hant/LC_MESSAGES/django.po
search_filter_sort/migrations/__init__.py
search_filter_sort/static/search_filter_sort/css/search_filter_sort.css
search_filter_sort/static/search_filter_sort/css/search_filter_sort.min.css
search_filter_sort/static/search_filter_sort/images/sort_asc.png
search_filter_sort/static/search_filter_sort/images/sort_asc_light.png
search_filter_sort/static/search_filter_sort/images/sort_both.png
search_filter_sort/static/search_filter_sort/images/sort_both_light.png
search_filter_sort/static/search_filter_sort/images/sort_desc.png
search_filter_sort/static/search_filter_sort/images/sort_desc_light.png
search_filter_sort/static/search_filter_sort/js/search_filter_sort.js
search_filter_sort/static/search_filter_sort/js/search_filter_sort.min.js
search_filter_sort/templates/search_filter_sort/checkbox_header.html
search_filter_sort/templates/search_filter_sort/checkbox_row.html
search_filter_sort/templates/search_filter_sort/pagination_page_navigation.html
search_filter_sort/templates/search_filter_sort/search_filter_sort.html
search_filter_sort/templates/search_filter_sort/sortable_col.html
search_filter_sort/utils/__init__.py
search_filter_sort/utils/constants.py
search_filter_sort/utils/errors.py
search_filter_sort/utils/misc.py
search_filter_sort/utils/prototype_testing.py
search_filter_sort/views/__init__.py
