Metadata-Version: 2.4
Name: django-search-filter-sort
Version: 0.4.1
Summary: Django app designed to help with the creation of list views with full functionality for searching, filtering, and sorting.
Home-page: https://github.com/Macainian/Django-Search-Filter-Sort
Author: Keith Hostetler
Author-email: robh@syscon-intl.com
License: MIT License
Classifier: Development Status :: 3 - Alpha
Classifier: License :: OSI Approved :: MIT License
Classifier: Intended Audience :: Developers
Classifier: Operating System :: OS Independent
Classifier: Programming Language :: Python
Classifier: Programming Language :: Python :: 2
Classifier: Programming Language :: Python :: 2.7
Classifier: Programming Language :: Python :: 3
Classifier: Programming Language :: Python :: 3.4
Classifier: Programming Language :: Python :: 3.5
Classifier: Topic :: Software Development :: Libraries :: Python Modules
License-File: LICENSE
Dynamic: author
Dynamic: author-email
Dynamic: classifier
Dynamic: home-page
Dynamic: license
Dynamic: license-file
Dynamic: summary
